tree_sitter_java/__init__.py
tree_sitter_java/_binding.abi3.so
tree_sitter_java/binding.c
tree_sitter_java/__init__.pyi
tree_sitter_java/py.typed
tree_sitter_java/queries/highlights.scm
tree_sitter_java/queries/tags.scm
tree_sitter_java-0.23.4.dist-info/top_level.txt
tree_sitter_java-0.23.4.dist-info/RECORD
tree_sitter_java-0.23.4.dist-info/LICENSE
tree_sitter_java-0.23.4.dist-info/METADATA
tree_sitter_java-0.23.4.dist-info/WHEEL
