Metadata-Version: 2.1
Name: tree-sitter-java
Version: 0.23.4
Summary: Java grammar for tree-sitter
Author-email: Ayman Nadeem <aymannadeem@github.com>, Max Brunsfeld <maxbrunsfeld@gmail.com>, Amaan Qureshi <amaanq12@gmail.com>
License: MIT
Project-URL: Homepage, https://github.com/tree-sitter/tree-sitter-java
Keywords: incremental,parsing,tree-sitter,java
Classifier: Intended Audience :: Developers
Classifier: License :: OSI Approved :: MIT License
Classifier: Topic :: Software Development :: Compilers
Classifier: Topic :: Text Processing :: Linguistic
Classifier: Typing :: Typed
Requires-Python: >=3.9
License-File: LICENSE
Provides-Extra: core
Requires-Dist: tree-sitter~=0.22; extra == "core"
